README.md
package_info.json
setup.py
th2_grpc_check1/__init__.py
th2_grpc_check1/check1.proto
th2_grpc_check1/check1_pb2.py
th2_grpc_check1/check1_pb2_grpc.py
th2_grpc_check1/check1_service.py
th2_grpc_check1.egg-info/PKG-INFO
th2_grpc_check1.egg-info/SOURCES.txt
th2_grpc_check1.egg-info/dependency_links.txt
th2_grpc_check1.egg-info/requires.txt
th2_grpc_check1.egg-info/top_level.txt