Metadata-Version: 2.1
Name: th2-grpc-check1
Version: 2.2.0
Summary: th2_grpc_check1
Home-page: https://github.com/th2-net/th2-grpc-check1
Author: TH2-devs
Author-email: th2-devs@exactprosystems.com
License: Apache License 2.0
Platform: UNKNOWN
Requires-Python: >=3.7
